examples/annotator.py
examples/app_types.py
examples/bench_performance.py
examples/bench_quality.py
examples/images_grid.py
examples/run.py
image_thr/__init__.py
image_thr/main.cpython-311-darwin.so
image_thr/main.py
image_thr-0.1.2.dist-info/licenses/LICENSE
image_thr-0.1.2.dist-info/METADATA
image_thr-0.1.2.dist-info/WHEEL
image_thr-0.1.2.dist-info/top_level.txt
image_thr-0.1.2.dist-info/RECORD
