Metadata-Version: 2.4
Name: image-thr
Version: 0.1.2
Summary: Image thresholding library
Author-email: "Sofo-Group, Inc" <info@sofo-group.com>
License: MIT License
Project-URL: Homepage, https://github.com/sofo-group/image-thr
Project-URL: Source, https://github.com/sofo-group/image-thr
Project-URL: Issues, https://github.com/sofo-group/image-thr/issues
Classifier: Programming Language :: Python :: 3
Classifier: License :: OSI Approved :: MIT License
Classifier: Operating System :: POSIX :: Linux
Requires-Python: >=3.11
License-File: LICENSE
Requires-Dist: numpy<1.27.dev0,>=1.26.4
Requires-Dist: opencv-python>=4.11.0.86
Requires-Dist: scikit-image>=0.26.0
Requires-Dist: scipy<1.14.dev0,>=1.13.1
Dynamic: license-file
